Metadata-Version: 1.0
Name: nrz-distributions
Version: 0.1
Summary: Gaussian distributions
Home-page: UNKNOWN
Author: Rosalie Zhu
Author-email: UNKNOWN
License: UNKNOWN
Platform: UNKNOWN
